<vdex xmlns="http://www.imsglobal.org/xsd/imsvdex_v1p0" orderSignificant="false" profileType="thesaurus" language="fr"> 
  <vocabName> 
    <langstring language="fr">Vocabulaire NORMETICv1.2: &#xE9;l&#xE9;ment 5.6 contexte</langstring> 
  </vocabName> 
  <vocabIdentifier isRegistered="false">http://eureka.ntic.org/vdex/NORMETICv1.2_element_5_6_contexte_voc.xml</vocabIdentifier> 
  <term validIndex="true" orderSignificant="false"> 
    <termIdentifier>&#xE9;ducation pr&#xE9;scolaire</termIdentifier> 
    <caption> 
      <langstring language="fr-CA">&#xE9;ducation pr&#xE9;scolaire</langstring> 
      <langstring language="en">kindergarten</langstring> 
    </caption> 
    <description> 
      <langstring language="fr-CA">&#xE9;ducation pr&#xE9;scolaire</langstring> 
      <langstring language="en">kindergarten</langstring> 
    </description> 
  </term> 
  <term validIndex="true" orderSignificant="false"> 
    <termIdentifier>&#xE9;ducation primaire</termIdentifier> 
    <caption> 
      <langstring language="en">primary education</langstring> 
      <langstring language="fr-CA">&#xE9;ducation primaire</langstring> 
    </caption> 
    <description> 
      <langstring language="en">primary education</langstring> 
      <langstring language="fr-CA">&#xE9;ducation primaire</langstring> 
    </description> 
  </term> 
  <term validIndex="true" orderSignificant="false"> 
    <termIdentifier>&#xE9;ducation secondaire</termIdentifier> 
    <caption> 
      <langstring language="fr-CA">&#xE9;ducation secondaire</langstring> 
      <langstring language="en">secondary education</langstring> 
    </caption> 
    <description> 
      <langstring language="en">secondary education</langstring> 
      <langstring language="fr-CA">&#xE9;ducation secondaire</langstring> 
    </description> 
  </term> 
  <term validIndex="true" orderSignificant="false"> 
    <termIdentifier>formation professionnelle</termIdentifier> 
    <caption> 
      <langstring language="fr-CA">formation professionnelle</langstring> 
      <langstring language="en">vocational training</langstring> 
    </caption> 
    <description> 
      <langstring language="fr-CA">formation professionnelle au secondaire</langstring> 
      <langstring language="en">vocational training at secondary school</langstring> 
    </description> 
  </term> 
  <term validIndex="true" orderSignificant="false"> 
    <termIdentifier>c&#xE9;gep</termIdentifier> 
    <caption> 
      <langstring language="en">cegep</langstring> 
      <langstring language="fr-CA">c&#xE9;gep</langstring> 
    </caption> 
    <description> 
      <langstring language="fr-CA">coll&#xE8;ge d'enseignement g&#xE9;n&#xE9;ral et professionnel</langstring> 
      <langstring language="en">college of general and vocational education</langstring> 
    </description> 
  </term> 
  <term validIndex="true" orderSignificant="false"> 
    <termIdentifier>formation technique</termIdentifier> 
    <caption> 
      <langstring language="en">technical education</langstring> 
      <langstring language="fr-CA">formation technique</langstring> 
    </caption> 
    <description> 
      <langstring language="en">vocational training at cegep</langstring> 
      <langstring language="fr-CA">formation professionnelle au c&#xE9;gep</langstring> 
    </description> 
  </term> 
  <term validIndex="true" orderSignificant="false"> 
    <termIdentifier>universit&#xE9; premier cycle</termIdentifier> 
    <caption> 
      <langstring language="fr-CA">universit&#xE9; premier cycle</langstring> 
      <langstring language="en">undergraduate education</langstring> 
    </caption> 
    <description> 
      <langstring language="en">undergraduate education</langstring> 
      <langstring language="fr-CA">universit&#xE9; premier cycle</langstring> 
    </description> 
  </term> 
  <term validIndex="true" orderSignificant="false"> 
    <termIdentifier>universit&#xE9; second cycle</termIdentifier> 
    <caption> 
      <langstring language="fr-CA">universit&#xE9; second cycle</langstring> 
      <langstring language="en">graduate education</langstring> 
    </caption> 
    <description> 
      <langstring language="fr-CA">universit&#xE9; second cycle</langstring> 
      <langstring language="en">graduate education</langstring> 
    </description> 
  </term> 
  <term validIndex="true" orderSignificant="false"> 
    <termIdentifier>universit&#xE9; troisi&#xE8;me cycle</termIdentifier> 
    <caption> 
      <langstring language="en">postgraduate education</langstring> 
      <langstring language="fr-CA">universit&#xE9; troisi&#xE8;me cycle</langstring> 
    </caption> 
    <description> 
      <langstring language="en">postgraduate education</langstring> 
      <langstring language="fr-CA">universit&#xE9; troisi&#xE8;me cycle</langstring> 
    </description> 
  </term> 
  <term validIndex="true" orderSignificant="false"> 
    <termIdentifier>formation continue</termIdentifier> 
    <caption> 
      <langstring language="fr-CA">formation continue</langstring> 
      <langstring language="en">continuous training</langstring> 
    </caption> 
    <description> 
      <langstring language="fr-CA">Ensemble des processus d&#x2019;apprentissage, formels ou autres, gr&#xE2;ce auxquels les individus consid&#xE9;r&#xE9;s comme adultes dans la soci&#xE9;t&#xE9; &#xE0; laquelle ils appartiennent d&#xE9;veloppent leurs aptitudes, enrichissent leurs connaissances et am&#xE9;liorent leurs qualifications techniques ou professionnelles, ou les r&#xE9;orientent en fonction de leurs propres besoins et de ceux de la soci&#xE9;t&#xE9;. (MELS)</langstring> 
    </description> 
  </term> 
  <term validIndex="true" orderSignificant="false"> 
    <termIdentifier>autre</termIdentifier> 
    <caption> 
      <langstring language="en">other</langstring> 
      <langstring language="fr-CA">autre</langstring> 
    </caption> 
    <description> 
      <langstring language="fr-CA">autre</langstring> 
      <langstring language="en">other</langstring> 
    </description> 
  </term> 
  <term validIndex="true" orderSignificant="false"> 
    <termIdentifier>formation en entreprise</termIdentifier> 
    <caption> 
      <langstring language="fr-CA">formation en entreprise</langstring> 
      <langstring language="en">corporate training</langstring> 
    </caption> 
    <description> 
      <langstring language="fr-CA">Formation sp&#xE9;cifique d&#xE9;velopp&#xE9;e pour r&#xE9;pondre aux besoins particuliers d''une entreprise.</langstring> 
      <langstring language="en">corporate training</langstring> 
    </description> 
  </term> 
  <metadata> 
    <vocabSource xmlns="http://eureka.coeus.ca/xsd/vdex_eureka_metadata.xsd"></vocabSource> 
    <vocabIsSystem xmlns="http://eureka.coeus.ca/xsd/vdex_eureka_metadata.xsd">true</vocabIsSystem> 
    <vocabIsRelationship xmlns="http://eureka.coeus.ca/xsd/vdex_eureka_metadata.xsd">false</vocabIsRelationship> 
  </metadata> 
</vdex> 